aboleth/__init__.py
aboleth/baselayers.py
aboleth/datasets.py
aboleth/distributions.py
aboleth/hlayers.py
aboleth/impute.py
aboleth/initialisers.py
aboleth/kernels.py
aboleth/layers.py
aboleth/losses.py
aboleth/prediction.py
aboleth/random.py
aboleth/util.py
aboleth/version.py
aboleth-0.9.0.dist-info/METADATA
aboleth-0.9.0.dist-info/RECORD
aboleth-0.9.0.dist-info/WHEEL
aboleth-0.9.0.dist-info/top_level.txt
tests/__init__.py
tests/conftest.py
tests/test_baselayers.py
tests/test_distributions.py
tests/test_hlayers.py
tests/test_impute.py
tests/test_initialisers.py
tests/test_kernels.py
tests/test_layers.py
tests/test_losses.py
tests/test_prediction.py
tests/test_utils.py
tests/util.py
