Metadata-Version: 2.1
Name: aboleth
Version: 0.9.0
Summary: Bayesian supervised deep learning with TensorFlow
Home-page: https://github.com/data61/aboleth
Author: Daniel Steinberg, Lachlan McCalman
Author-email: daniel.steinberg@data61.csiro.au
License: Apache 2.0
Keywords: aboleth
Platform: UNKNOWN
Classifier: Development Status :: 4 - Beta
Classifier: Operating System :: POSIX
Classifier: Natural Language :: English
Classifier: Programming Language :: Python
Classifier: Programming Language :: Python :: 3
Classifier: Programming Language :: Python :: 3.5
Classifier: Programming Language :: Python :: 3.6
Classifier: Intended Audience :: Science/Research
Classifier: Intended Audience :: Developers
Classifier: Topic :: Software Development :: Libraries :: Python Modules
Classifier: Topic :: Scientific/Engineering :: Artificial Intelligence
Classifier: Topic :: Scientific/Engineering :: Information Analysis
Provides-Extra: dev
Provides-Extra: demos
Requires-Dist: tensorflow (>=1.10.0)
Requires-Dist: tensorflow-probability (>=0.3)
Requires-Dist: scipy (>=0.18.1)
Requires-Dist: six (>=1.10.0)
Provides-Extra: demos
Requires-Dist: bokeh (>=0.12.4); extra == 'demos'
Requires-Dist: pandas (>=0.20.3); extra == 'demos'
Requires-Dist: scikit-learn (>=0.18.1); extra == 'demos'
Provides-Extra: dev
Requires-Dist: sphinx (>=1.4.8); extra == 'dev'
Requires-Dist: pytest (>=3.1.0); extra == 'dev'
Requires-Dist: pytest-mock (>=1.6.0); extra == 'dev'
Requires-Dist: pytest-cov (>=2.5.1); extra == 'dev'
Requires-Dist: pytest-flake8 (>=0.8.1); extra == 'dev'
Requires-Dist: flake8-docstrings (>=1.1.0); extra == 'dev'
Requires-Dist: scikit-learn (>=0.18.1); extra == 'dev'
